{
  "sections": {
    "image_with_text_CiXKT3": {
      "type": "image-with-text",
      "blocks": {
        "heading_yfFb7U": {
          "type": "heading",
          "settings": {
            "heading": "Explore our store",
            "heading_size": "h0"
          }
        },
        "text_mNWkKg": {
          "type": "text",
          "settings": {
            "text": "<p>Explore the latest trends in designer clothing at our reputable clother stores.<\/p>",
            "text_style": "body"
          }
        },
        "button_DKe3Gb": {
          "type": "button",
          "settings": {
            "button_label": "Let's go",
            "button_link": "shopify:\/\/collections\/all",
            "button_style_secondary": false
          }
        }
      },
      "block_order": [
        "heading_yfFb7U",
        "text_mNWkKg",
        "button_DKe3Gb"
      ],
      "settings": {
        "image": "shopify:\/\/shop_images\/clark-street-mercantile-P3pI6xzovu0-unsplash_1.jpg",
        "height": "medium",
        "desktop_image_width": "small",
        "layout": "image_first",
        "desktop_content_position": "top",
        "desktop_content_alignment": "right",
        "content_layout": "no-overlap",
        "section_color_scheme": "scheme-c53d0188-c0d2-45a6-839a-1cc97c8a7f6d",
        "color_scheme": "scheme-4",
        "image_behavior": "none",
        "mobile_content_alignment": "center",
        "padding_top": 36,
        "padding_bottom": 36
      }
    },
    "17083396204c1ea5e3": {
      "type": "apps",
      "blocks": {
        "hura_theme_blocks_gap_block_eLtaqr": {
          "type": "shopify:\/\/apps\/hura-theme-blocks\/blocks\/gap-block\/5b288e0f-cbe6-47c0-909d-b0904b0ad6dd",
          "settings": {
            "bg_color": "rgba(0,0,0,0)",
            "height": 50
          }
        },
        "hura_theme_blocks_faq_block_J3Lc3i": {
          "type": "shopify:\/\/apps\/hura-theme-blocks\/blocks\/faq-block\/5b288e0f-cbe6-47c0-909d-b0904b0ad6dd",
          "settings": {
            "question_color": "#000000",
            "answer_color": "#696969",
            "question_1": "How can I place an order?",
            "answer_1": "<p>To place an order, simply browse our collection online or visit our store. Once you've found the items you love, add them to your cart and proceed to checkout. Follow the prompts to enter your shipping and payment information, and your order will be on its way!<\/p>",
            "question_2": "What payment methods do you accept?",
            "answer_2": "<p>We accept various payment methods, including credit\/debit cards, PayPal, and other secure online payment platforms. Rest assured, your payment information is always kept safe and encrypted for your security.<\/p>",
            "question_3": "Do you offer international shipping?",
            "answer_3": "<p>Yes, we offer international shipping to many countries around the world. Shipping costs and delivery times may vary depending on your location. During checkout, you can select your country to view the available shipping options.<\/p>",
            "question_4": "What is your return policy?",
            "answer_4": "<p>We want you to be completely satisfied with your purchase. If for any reason you're not happy with your order, you may return it within 30 days of receiving it for a refund or exchange. Please see our Returns page for more information on how to initiate a return.<\/p>",
            "question_5": "",
            "answer_5": "",
            "question_6": "",
            "answer_6": "",
            "question_7": "",
            "answer_7": "",
            "question_8": "",
            "answer_8": "",
            "question_9": "",
            "answer_9": "",
            "question_10": "",
            "answer_10": ""
          }
        }
      },
      "block_order": [
        "hura_theme_blocks_gap_block_eLtaqr",
        "hura_theme_blocks_faq_block_J3Lc3i"
      ],
      "settings": {
        "include_margins": true
      }
    },
    "1708339641487714be": {
      "type": "apps",
      "blocks": {
        "hura_theme_blocks_gap_block_kTL3Dg": {
          "type": "shopify:\/\/apps\/hura-theme-blocks\/blocks\/gap-block\/5b288e0f-cbe6-47c0-909d-b0904b0ad6dd",
          "settings": {
            "bg_color": "rgba(0,0,0,0)",
            "height": 50
          }
        },
        "hura_theme_blocks_html_block_XMNzYE": {
          "type": "shopify:\/\/apps\/hura-theme-blocks\/blocks\/html-block\/5b288e0f-cbe6-47c0-909d-b0904b0ad6dd",
          "settings": {
            "custom_html": "",
            "custom_liquid": "<div class=\"contact-info\">\n    <p>Email: <a href=\"mailto:{{ shop.email }}\">{{ shop.email }}<\/a><\/p>\n    <p>Phone: {{ shop.phone }}<\/p>\n<\/div>"
          }
        }
      },
      "block_order": [
        "hura_theme_blocks_gap_block_kTL3Dg",
        "hura_theme_blocks_html_block_XMNzYE"
      ],
      "settings": {
        "include_margins": true
      }
    }
  },
  "order": [
    "image_with_text_CiXKT3",
    "17083396204c1ea5e3",
    "1708339641487714be"
  ]
}
